{
  "projects": [
    {
      "titulo": "Dan Legal icr",
      "orcamento": "1050",
      "motivo": "Um projeto para testar a capacidade do time",
      "category": {
        "id": "4",
        "name": "Planejamento"
      },
      "costs": 0,
      "services": [],
      "id": 1
    },
    {
      "titulo": "Jogo da Orb",
      "orcamento": "100000",
      "motivo": "Um projeto para testar a capacidade do time",
      "category": {
        "id": "1",
        "name": "Infra"
      },
      "costs": 0,
      "services": [],
      "id": 2
    }
  ],
  "categories": [
    {
      "id": 1,
      "name": "Infra"
    },
    {
      "id": 2,
      "name": "Desenvolvimento"
    },
    {
      "id": 3,
      "name": "Design"
    },
    {
      "id": 4,
      "name": "Planejamento"
    }
  ]
}